{
  "project_info": {
    "project_number": "53108303466",
    "firebase_url": "https://purelogregui.firebaseio.com",
    "project_id": "purelogregui",
    "storage_bucket": "purelogregui.appspot.com"
  },
  "client": [
    {
      "client_info": {
        "mobilesdk_app_id": "1:53108303466:android:e5488fc421a09e2c954c13",
        "android_client_info": {
          "package_name": "com.example.purelogregui"
        }
      },
      "oauth_client": [
        {
          "client_id": "53108303466-d7j40aktudj53aisgrk73cmk0nducl30.apps.googleusercontent.com",
          "client_type": 3
        }
      ],
      "api_key": [
        {
          "current_key": "AIzaSyAVMfdVCnX4bDOmSMxV562L7P8eHTxPO1k"
        }
      ],
      "services": {
        "appinvite_service": {
          "other_platform_oauth_client": [
            {
              "client_id": "53108303466-d7j40aktudj53aisgrk73cmk0nducl30.apps.googleusercontent.com",
              "client_type": 3
            }
          ]
        }
      }
    }
  ],
  "configuration_version": "1"
}